moveread/annotations/__init__.py
moveread/annotations/__init__.pyi
moveread/annotations/games.py
moveread/annotations/images.py
moveread/annotations/players.py
moveread/annotations/sheets.py
moveread/annotations/tsgen.py
moveread_annotations-0.1.12.dist-info/METADATA
moveread_annotations-0.1.12.dist-info/WHEEL
moveread_annotations-0.1.12.dist-info/entry_points.txt
moveread_annotations-0.1.12.dist-info/top_level.txt
moveread_annotations-0.1.12.dist-info/RECORD
